pyjems/Illuminate/Auth/Access/Gate.py
pyjems/Illuminate/Auth/AuthServiceProvider.py
pyjems/Illuminate/Auth/Middleware/Authenticate.py
pyjems/Illuminate/Collections/Arr.py
pyjems/Illuminate/Collections/Collection.py
pyjems/Illuminate/Collections/Enumerable.py
pyjems/Illuminate/Collections/Traits/EnumeratesValues.py
pyjems/Illuminate/Collections/helpers.py
pyjems/Illuminate/Conditionable/Conditionable.py
pyjems/Illuminate/Config/Repository.py
pyjems/Illuminate/Container/Container.py
pyjems/Illuminate/Contracts/Auth/Access/Gate.py
pyjems/Illuminate/Contracts/Collections/Collection.py
pyjems/Illuminate/Contracts/Console/Kernel.py
pyjems/Illuminate/Contracts/Container/Container.py
pyjems/Illuminate/Contracts/Debug/ExceptionHandler.py
pyjems/Illuminate/Contracts/Events/Dispatcher.py
pyjems/Illuminate/Contracts/Foundation/Application.py
pyjems/Illuminate/Contracts/Http/Kernel.py
pyjems/Illuminate/Contracts/Http/Request.py
pyjems/Illuminate/Contracts/Http/Response.py
pyjems/Illuminate/Contracts/Resolvable.py
pyjems/Illuminate/Contracts/Routing/Router.py
pyjems/Illuminate/Contracts/Support/JsonSerializable.py
pyjems/Illuminate/Contracts/Support/ServiceProvider.py
pyjems/Illuminate/Database/Serializable.py
pyjems/Illuminate/Events/Dispatcher.py
pyjems/Illuminate/Events/EventServiceProvider.py
pyjems/Illuminate/Exceptions/Handler.py
pyjems/Illuminate/Exceptions/RouteNotFoundException.py
pyjems/Illuminate/Exceptions/UnauthorizedAccessException.py
pyjems/Illuminate/Foundation/Application.py
pyjems/Illuminate/Foundation/Auth/User.py
pyjems/Illuminate/Foundation/Bootstrap/BootProviders.py
pyjems/Illuminate/Foundation/Bootstrap/HandleExceptions.py
pyjems/Illuminate/Foundation/Bootstrap/LoadConfiguration.py
pyjems/Illuminate/Foundation/Bootstrap/LoadEnvironmentVariables.py
pyjems/Illuminate/Foundation/Bootstrap/RegisterFacades.py
pyjems/Illuminate/Foundation/Bootstrap/RegisterProviders.py
pyjems/Illuminate/Foundation/Configuration/App.py
pyjems-0.1.0.dist-info/LICENSE.md
pyjems-0.1.0.dist-info/METADATA
pyjems-0.1.0.dist-info/WHEEL
pyjems-0.1.0.dist-info/RECORD
