Metadata-Version: 2.1
Name: pyjems
Version: 0.1.0
Summary: PyJems - Python MVC framework
License: MIT
Author: Krunal Dodiya
Author-email: kunal.dodiya1@gmail.com
Requires-Python: >=3.10,<4.0
Classifier: License :: OSI Approved :: MIT License
Classifier: Programming Language :: Python :: 3
Classifier: Programming Language :: Python :: 3.10
Classifier: Programming Language :: Python :: 3.11
Classifier: Programming Language :: Python :: 3.12
Classifier: Programming Language :: Python :: 3.13
Requires-Dist: colorama (>=0.4.6,<0.5.0)
Requires-Dist: pendulum (>=3.0.0,<4.0.0)
Requires-Dist: pluralizer (>=1.2.0,<2.0.0)
Requires-Dist: python-dotenv (>=1.0.1,<2.0.0)
Project-URL: documentation, https://pyjems.gitbook.io/docs
Project-URL: homepage, https://www.proalgotrader.com
Project-URL: repository, https://github.com/pyjems/framework
